asgi_caches/__init__.py
asgi_caches/__version__.py
asgi_caches/decorators.py
asgi_caches/exceptions.py
asgi_caches/middleware.py
asgi_caches/utils/__init__.py
asgi_caches/utils/cache.py
asgi_caches/utils/logging.py
asgi_caches/utils/misc.py
asgi_caches-0.3.1.dist-info/LICENSE
asgi_caches-0.3.1.dist-info/METADATA
asgi_caches-0.3.1.dist-info/WHEEL
asgi_caches-0.3.1.dist-info/top_level.txt
asgi_caches-0.3.1.dist-info/RECORD
