Metadata-Version: 2.1
Name: asgi-caches
Version: 0.3.1
Summary: Server-side HTTP caching for ASGI applications, inspired by Django's cache framework
Home-page: http://github.com/florimondmanca/asgi-caches
Author: Florimond Manca
Author-email: florimond.manca@gmail.com
License: MIT
Platform: UNKNOWN
Classifier: Development Status :: 3 - Alpha
Classifier: Intended Audience :: Developers
Classifier: Operating System :: OS Independent
Classifier: Programming Language :: Python :: 3
Classifier: Programming Language :: Python :: 3.6
Classifier: Programming Language :: Python :: 3.7
Classifier: Programming Language :: Python :: 3.8
Requires-Python: >=3.6
Requires-Dist: async-caches (==0.*)
Requires-Dist: starlette (==0.*)
